RiotGames/Spectator.py
RiotGames/ThirdPartyCode.py
RiotGames/__init__.py
RiotGames/API/Champion.py
RiotGames/API/ChampionMastery.py
RiotGames/API/LOLStatus.py
RiotGames/API/League.py
RiotGames/API/LeagueEXP.py
RiotGames/API/Match.py
RiotGames/API/RiotApi.py
RiotGames/API/Summoner.py
RiotGames/API/__init__.py
RiotGames/Spectator/__init__.py
RiotGames/Summoner/Account.py
RiotGames/Summoner/Ranked.py
RiotGames/Summoner/__init__.py
RiotGames-1.1.0.dist-info/LICENSE
RiotGames-1.1.0.dist-info/METADATA
RiotGames-1.1.0.dist-info/WHEEL
RiotGames-1.1.0.dist-info/top_level.txt
RiotGames-1.1.0.dist-info/RECORD
